{"package":"ankiR","priority":null,"maintainer":"Christos Longros <chris.longros@gmail.com>","issues":[{}],"results":[[{"flavor":"r-devel-linux-x86_64-debian-clang","version":"0.6.0","check_status":"OK","flags":"","t_install":12.89,"t_check":81.84,"t_total":94.73},{"flavor":"r-devel-linux-x86_64-debian-gcc","version":"0.6.0","check_status":"OK","flags":"","t_install":7.64,"t_check":55.94,"t_total":63.58},{"flavor":"r-devel-linux-x86_64-fedora-clang","version":"0.6.0","check_status":"OK","flags":"","t_install":19.0,"t_check":124.41999999999999,"t_total":143.42},{"flavor":"r-devel-linux-x86_64-fedora-gcc","version":"0.6.0","check_status":"OK","flags":"","t_install":19.0,"t_check":127.16999999999999,"t_total":146.17},{"flavor":"r-devel-macos-arm64","version":"0.6.0","check_status":"OK","flags":"","t_install":3.0,"t_check":23.0,"t_total":26.0},{"flavor":"r-devel-windows-x86_64","version":"0.6.0","check_status":"OK","flags":"","t_install":13.0,"t_check":113.0,"t_total":126.0},{"flavor":"r-patched-linux-x86_64","version":"0.6.0","check_status":"OK","flags":"","t_install":12.06,"t_check":71.7,"t_total":83.76},{"flavor":"r-release-linux-x86_64","version":"0.6.0","check_status":"OK","flags":"","t_install":11.03,"t_check":71.94,"t_total":82.97},{"flavor":"r-release-macos-arm64","version":"0.6.0","check_status":"OK","flags":"","t_install":2.0,"t_check":24.0,"t_total":26.0},{"flavor":"r-release-macos-x86_64","version":"0.6.0","check_status":"OK","flags":"","t_install":8.0,"t_check":173.0,"t_total":181.0},{"flavor":"r-release-windows-x86_64","version":"0.6.0","check_status":"OK","flags":"","t_install":15.0,"t_check":110.0,"t_total":125.0},{"flavor":"r-oldrel-macos-arm64","version":"0.6.0","check_status":"OK","flags":"","t_install":3.0,"t_check":29.0,"t_total":32.0},{"flavor":"r-oldrel-macos-x86_64","version":"0.6.0","check_status":"OK","flags":"","t_install":8.0,"t_check":149.0,"t_total":157.0},{"flavor":"r-oldrel-windows-x86_64","version":"0.6.0","check_status":"OK","flags":"","t_install":19.0,"t_check":129.0,"t_total":148.0}]]}
