{"package":"autoslider.core","priority":null,"maintainer":"Joe Zhu <joe.zhu@roche.com>","issues":[{}],"results":[[{"flavor":"r-devel-linux-x86_64-debian-clang","version":"0.2.3","check_status":"OK","flags":"","t_install":21.84,"t_check":549.31,"t_total":571.15},{"flavor":"r-devel-linux-x86_64-debian-gcc","version":"0.2.4","check_status":"OK","flags":"","t_install":14.89,"t_check":357.34,"t_total":372.23},{"flavor":"r-devel-linux-x86_64-fedora-clang","version":"0.2.4","check_status":"OK","flags":"","t_install":null,"t_check":null,"t_total":1030.06},{"flavor":"r-devel-linux-x86_64-fedora-gcc","version":"0.2.4","check_status":"OK","flags":"","t_install":null,"t_check":null,"t_total":944.33},{"flavor":"r-devel-windows-x86_64","version":"0.2.3","check_status":"OK","flags":"","t_install":25.0,"t_check":503.0,"t_total":528.0},{"flavor":"r-patched-linux-x86_64","version":"0.2.3","check_status":"OK","flags":"","t_install":23.25,"t_check":517.61,"t_total":540.86},{"flavor":"r-release-linux-x86_64","version":"0.2.3","check_status":"OK","flags":"","t_install":21.55,"t_check":514.3,"t_total":535.85},{"flavor":"r-release-macos-arm64","version":"0.2.4","check_status":"OK","flags":"","t_install":null,"t_check":null,"t_total":150.0},{"flavor":"r-release-macos-x86_64","version":"0.2.4","check_status":"OK","flags":"","t_install":null,"t_check":null,"t_total":276.0},{"flavor":"r-release-windows-x86_64","version":"0.2.3","check_status":"OK","flags":"","t_install":24.0,"t_check":498.0,"t_total":522.0},{"flavor":"r-oldrel-macos-arm64","version":"0.2.4","check_status":"NOTE","flags":"","t_install":null,"t_check":null,"t_total":176.0},{"flavor":"r-oldrel-macos-x86_64","version":"0.2.4","check_status":"NOTE","flags":"","t_install":null,"t_check":null,"t_total":291.0},{"flavor":"r-oldrel-windows-x86_64","version":"0.2.3","check_status":"NOTE","flags":"","t_install":32.0,"t_check":720.0,"t_total":752.0}]]}
