{"package":"BayesChange","priority":null,"maintainer":"Luca Danese <l.danese1@campus.unimib.it>","issues":[{}],"results":[[{"flavor":"r-devel-linux-x86_64-debian-clang","version":"2.3.0","check_status":"OK","flags":"","t_install":50.22,"t_check":233.52,"t_total":283.74},{"flavor":"r-devel-linux-x86_64-debian-gcc","version":"2.3.0","check_status":"OK","flags":"","t_install":34.87,"t_check":170.54,"t_total":205.41},{"flavor":"r-devel-linux-x86_64-fedora-clang","version":"2.3.0","check_status":"OK","flags":"","t_install":58.0,"t_check":345.67,"t_total":403.67},{"flavor":"r-devel-linux-x86_64-fedora-gcc","version":"2.3.0","check_status":"OK","flags":"","t_install":93.0,"t_check":366.07,"t_total":459.07},{"flavor":"r-devel-windows-x86_64","version":"2.3.0","check_status":"OK","flags":"","t_install":52.0,"t_check":277.0,"t_total":329.0},{"flavor":"r-patched-linux-x86_64","version":"2.3.0","check_status":"OK","flags":"","t_install":48.54,"t_check":211.52,"t_total":260.06},{"flavor":"r-release-linux-x86_64","version":"2.3.0","check_status":"OK","flags":"","t_install":83.22,"t_check":223.25,"t_total":306.47},{"flavor":"r-release-macos-arm64","version":"2.3.0","check_status":"OK","flags":"","t_install":10.0,"t_check":79.0,"t_total":89.0},{"flavor":"r-release-macos-x86_64","version":"2.3.0","check_status":"OK","flags":"","t_install":35.0,"t_check":327.0,"t_total":362.0},{"flavor":"r-release-windows-x86_64","version":"2.3.0","check_status":"OK","flags":"","t_install":52.0,"t_check":279.0,"t_total":331.0},{"flavor":"r-oldrel-macos-arm64","version":"2.3.0","check_status":"OK","flags":"","t_install":10.0,"t_check":74.0,"t_total":84.0},{"flavor":"r-oldrel-macos-x86_64","version":"2.3.0","check_status":"OK","flags":"","t_install":36.0,"t_check":237.0,"t_total":273.0},{"flavor":"r-oldrel-windows-x86_64","version":"2.3.0","check_status":"OK","flags":"","t_install":68.0,"t_check":307.0,"t_total":375.0}]]}
