{"package":"BioStatR","priority":null,"maintainer":"Frederic Bertrand <frederic.bertrand@utt.fr>","issues":[{}],"results":[[{"flavor":"r-devel-linux-x86_64-debian-clang","version":"4.0.1","check_status":"NOTE","flags":"","t_install":4.94,"t_check":47.99,"t_total":52.93},{"flavor":"r-devel-linux-x86_64-debian-gcc","version":"4.0.1","check_status":"NOTE","flags":"","t_install":3.58,"t_check":34.24,"t_total":37.82},{"flavor":"r-devel-linux-x86_64-fedora-clang","version":"4.0.1","check_status":"OK","flags":"","t_install":null,"t_check":null,"t_total":74.57},{"flavor":"r-devel-linux-x86_64-fedora-gcc","version":"4.0.1","check_status":"OK","flags":"","t_install":null,"t_check":null,"t_total":73.99},{"flavor":"r-devel-windows-x86_64","version":"4.0.1","check_status":"OK","flags":"","t_install":6.0,"t_check":62.0,"t_total":68.0},{"flavor":"r-patched-linux-x86_64","version":"4.0.1","check_status":"NOTE","flags":"","t_install":5.17,"t_check":45.41,"t_total":50.58},{"flavor":"r-release-linux-x86_64","version":"4.0.1","check_status":"NOTE","flags":"","t_install":4.4,"t_check":45.07,"t_total":49.47},{"flavor":"r-release-macos-arm64","version":"4.0.1","check_status":"OK","flags":"","t_install":null,"t_check":null,"t_total":30.0},{"flavor":"r-release-macos-x86_64","version":"4.0.1","check_status":"OK","flags":"","t_install":null,"t_check":null,"t_total":54.0},{"flavor":"r-release-windows-x86_64","version":"4.0.1","check_status":"OK","flags":"","t_install":7.0,"t_check":64.0,"t_total":71.0},{"flavor":"r-oldrel-macos-arm64","version":"4.0.1","check_status":"OK","flags":"","t_install":null,"t_check":null,"t_total":25.0},{"flavor":"r-oldrel-macos-x86_64","version":"4.0.1","check_status":"OK","flags":"","t_install":null,"t_check":null,"t_total":36.0},{"flavor":"r-oldrel-windows-x86_64","version":"4.0.1","check_status":"OK","flags":"","t_install":8.0,"t_check":72.0,"t_total":80.0}]]}
