{"package":"bmstdr","priority":null,"maintainer":"Sujit K. Sahu <S.K.Sahu@soton.ac.uk>","issues":[{}],"results":[[{"flavor":"r-devel-linux-x86_64-debian-clang","version":"0.8.2","check_status":"OK","flags":"","t_install":508.91,"t_check":544.61,"t_total":1053.52},{"flavor":"r-devel-linux-x86_64-debian-gcc","version":"0.8.2","check_status":"OK","flags":"","t_install":362.8,"t_check":406.9,"t_total":769.7},{"flavor":"r-devel-linux-x86_64-fedora-clang","version":"0.8.2","check_status":"OK","flags":"","t_install":600.0,"t_check":1011.6300000000001,"t_total":1611.63},{"flavor":"r-devel-linux-x86_64-fedora-gcc","version":"0.8.2","check_status":"OK","flags":"","t_install":1140.0,"t_check":1019.4099999999999,"t_total":2159.41},{"flavor":"r-patched-linux-x86_64","version":"0.8.2","check_status":"OK","flags":"","t_install":558.91,"t_check":568.99,"t_total":1127.9},{"flavor":"r-release-linux-x86_64","version":"0.8.2","check_status":"OK","flags":"","t_install":539.17,"t_check":563.17,"t_total":1102.34},{"flavor":"r-release-macos-arm64","version":"0.8.2","check_status":"OK","flags":"","t_install":107.0,"t_check":56.0,"t_total":163.0},{"flavor":"r-release-macos-x86_64","version":"0.8.2","check_status":"OK","flags":"","t_install":315.0,"t_check":343.0,"t_total":658.0},{"flavor":"r-release-windows-x86_64","version":"0.8.2","check_status":"OK","flags":"","t_install":517.0,"t_check":486.0,"t_total":1003.0},{"flavor":"r-oldrel-macos-arm64","version":"0.8.2","check_status":"OK","flags":"","t_install":null,"t_check":null,"t_total":null},{"flavor":"r-oldrel-macos-x86_64","version":"0.8.2","check_status":"OK","flags":"","t_install":293.0,"t_check":55.0,"t_total":348.0},{"flavor":"r-oldrel-windows-x86_64","version":"0.8.2","check_status":"OK","flags":"","t_install":633.0,"t_check":686.0,"t_total":1319.0}]]}
