{"package":"climwin","priority":null,"maintainer":"Liam D. Bailey <liam.bailey@liamdbailey.com>","issues":[{}],"results":[[{"flavor":"r-devel-linux-x86_64-debian-clang","version":"1.2.31","check_status":"OK","flags":"","t_install":22.01,"t_check":266.11,"t_total":288.12},{"flavor":"r-devel-linux-x86_64-debian-gcc","version":"1.2.31","check_status":"OK","flags":"","t_install":14.97,"t_check":210.25,"t_total":225.22},{"flavor":"r-devel-linux-x86_64-fedora-clang","version":"1.2.31","check_status":"OK","flags":"","t_install":null,"t_check":null,"t_total":470.55},{"flavor":"r-devel-linux-x86_64-fedora-gcc","version":"1.2.31","check_status":"OK","flags":"","t_install":null,"t_check":null,"t_total":506.42},{"flavor":"r-devel-windows-x86_64","version":"1.2.31","check_status":"OK","flags":"","t_install":21.0,"t_check":304.0,"t_total":325.0},{"flavor":"r-patched-linux-x86_64","version":"1.2.31","check_status":"OK","flags":"","t_install":21.47,"t_check":288.71,"t_total":310.18},{"flavor":"r-release-linux-x86_64","version":"1.2.31","check_status":"OK","flags":"","t_install":19.43,"t_check":287.61,"t_total":307.04},{"flavor":"r-release-macos-arm64","version":"1.2.31","check_status":"OK","flags":"","t_install":null,"t_check":null,"t_total":158.0},{"flavor":"r-release-macos-x86_64","version":"1.2.31","check_status":"OK","flags":"","t_install":null,"t_check":null,"t_total":301.0},{"flavor":"r-release-windows-x86_64","version":"1.2.31","check_status":"OK","flags":"","t_install":20.0,"t_check":308.0,"t_total":328.0},{"flavor":"r-oldrel-macos-arm64","version":"1.2.31","check_status":"OK","flags":"","t_install":null,"t_check":null,"t_total":194.0},{"flavor":"r-oldrel-macos-x86_64","version":"1.2.31","check_status":"OK","flags":"","t_install":null,"t_check":null,"t_total":254.0},{"flavor":"r-oldrel-windows-x86_64","version":"1.2.31","check_status":"OK","flags":"","t_install":27.0,"t_check":409.0,"t_total":436.0}]]}
