{"package":"diseasemapping","priority":null,"maintainer":"Patrick Brown <patrick.brown@utoronto.ca>","issues":[{}],"results":[[{"flavor":"r-devel-linux-x86_64-debian-clang","version":"2.0.6","check_status":"OK","flags":"","t_install":20.69,"t_check":244.95,"t_total":265.64},{"flavor":"r-devel-linux-x86_64-debian-gcc","version":"2.0.6","check_status":"OK","flags":"","t_install":14.16,"t_check":152.13,"t_total":166.29},{"flavor":"r-devel-linux-x86_64-fedora-clang","version":"2.0.6","check_status":"OK","flags":"","t_install":null,"t_check":null,"t_total":428.33},{"flavor":"r-devel-linux-x86_64-fedora-gcc","version":"2.0.6","check_status":"OK","flags":"","t_install":null,"t_check":null,"t_total":1108.23},{"flavor":"r-devel-windows-x86_64","version":"2.0.6","check_status":"OK","flags":"","t_install":25.0,"t_check":203.0,"t_total":228.0},{"flavor":"r-patched-linux-x86_64","version":"2.0.6","check_status":"OK","flags":"","t_install":22.62,"t_check":234.58,"t_total":257.2},{"flavor":"r-release-linux-x86_64","version":"2.0.6","check_status":"OK","flags":"","t_install":23.05,"t_check":233.44,"t_total":256.49},{"flavor":"r-release-macos-arm64","version":"2.0.6","check_status":"OK","flags":"","t_install":null,"t_check":null,"t_total":98.0},{"flavor":"r-release-macos-x86_64","version":"2.0.6","check_status":"OK","flags":"","t_install":null,"t_check":null,"t_total":220.0},{"flavor":"r-release-windows-x86_64","version":"2.0.6","check_status":"OK","flags":"","t_install":24.0,"t_check":198.0,"t_total":222.0},{"flavor":"r-oldrel-macos-arm64","version":"2.0.6","check_status":"NOTE","flags":"","t_install":null,"t_check":null,"t_total":88.0},{"flavor":"r-oldrel-macos-x86_64","version":"2.0.6","check_status":"NOTE","flags":"","t_install":null,"t_check":null,"t_total":153.0},{"flavor":"r-oldrel-windows-x86_64","version":"2.0.6","check_status":"OK","flags":"","t_install":21.0,"t_check":284.0,"t_total":305.0}]]}
