{"package":"Dtableone","priority":null,"maintainer":"Youngmi Park <02141@snubh.org>","issues":[{}],"results":[[{"flavor":"r-devel-linux-x86_64-debian-clang","version":"1.1.0","check_status":"OK","flags":"","t_install":13.13,"t_check":103.45,"t_total":116.58},{"flavor":"r-devel-linux-x86_64-debian-gcc","version":"1.1.0","check_status":"OK","flags":"","t_install":8.71,"t_check":77.53,"t_total":86.24},{"flavor":"r-devel-linux-x86_64-fedora-clang","version":"1.1.0","check_status":"OK","flags":"","t_install":31.0,"t_check":148.89,"t_total":179.89},{"flavor":"r-devel-linux-x86_64-fedora-gcc","version":"1.1.0","check_status":"OK","flags":"","t_install":29.0,"t_check":143.55,"t_total":172.55},{"flavor":"r-devel-windows-x86_64","version":"1.1.0","check_status":"OK","flags":"","t_install":14.0,"t_check":98.0,"t_total":112.0},{"flavor":"r-patched-linux-x86_64","version":"1.1.0","check_status":"OK","flags":"","t_install":11.63,"t_check":96.75,"t_total":108.38},{"flavor":"r-release-linux-x86_64","version":"1.1.0","check_status":"OK","flags":"","t_install":12.22,"t_check":97.74,"t_total":109.96},{"flavor":"r-release-macos-arm64","version":"1.1.0","check_status":"OK","flags":"","t_install":null,"t_check":null,"t_total":null},{"flavor":"r-release-macos-x86_64","version":"1.1.0","check_status":"OK","flags":"","t_install":11.0,"t_check":78.0,"t_total":89.0},{"flavor":"r-release-windows-x86_64","version":"1.1.0","check_status":"OK","flags":"","t_install":14.0,"t_check":98.0,"t_total":112.0},{"flavor":"r-oldrel-macos-arm64","version":"1.1.0","check_status":"OK","flags":"","t_install":null,"t_check":null,"t_total":null},{"flavor":"r-oldrel-macos-x86_64","version":"1.1.0","check_status":"OK","flags":"","t_install":9.0,"t_check":67.0,"t_total":76.0},{"flavor":"r-oldrel-windows-x86_64","version":"1.1.0","check_status":"OK","flags":"","t_install":19.0,"t_check":133.0,"t_total":152.0}]]}
