{"package":"dyngen","priority":null,"maintainer":"Robrecht Cannoodt <rcannood@gmail.com>","issues":[{}],"results":[[{"flavor":"r-devel-linux-x86_64-debian-clang","version":"1.0.5","check_status":"NOTE","flags":"","t_install":20.82,"t_check":224.95,"t_total":245.77},{"flavor":"r-devel-linux-x86_64-debian-gcc","version":"1.0.5","check_status":"NOTE","flags":"","t_install":14.04,"t_check":146.0,"t_total":160.04},{"flavor":"r-devel-linux-x86_64-fedora-clang","version":"1.0.5","check_status":"NOTE","flags":"","t_install":141.0,"t_check":263.19,"t_total":404.19},{"flavor":"r-devel-linux-x86_64-fedora-gcc","version":"1.0.5","check_status":"NOTE","flags":"","t_install":128.0,"t_check":286.16,"t_total":414.16},{"flavor":"r-devel-windows-x86_64","version":"1.0.5","check_status":"NOTE","flags":"","t_install":23.0,"t_check":211.0,"t_total":234.0},{"flavor":"r-patched-linux-x86_64","version":"1.0.5","check_status":"NOTE","flags":"","t_install":25.09,"t_check":198.49,"t_total":223.58},{"flavor":"r-release-linux-x86_64","version":"1.0.5","check_status":"NOTE","flags":"","t_install":20.99,"t_check":207.33,"t_total":228.32},{"flavor":"r-release-macos-arm64","version":"1.0.5","check_status":"NOTE","flags":"","t_install":9.0,"t_check":99.0,"t_total":108.0},{"flavor":"r-release-macos-x86_64","version":"1.0.5","check_status":"NOTE","flags":"","t_install":17.0,"t_check":176.0,"t_total":193.0},{"flavor":"r-release-windows-x86_64","version":"1.0.5","check_status":"NOTE","flags":"","t_install":23.0,"t_check":208.0,"t_total":231.0},{"flavor":"r-oldrel-macos-arm64","version":"1.0.5","check_status":"NOTE","flags":"","t_install":9.0,"t_check":88.0,"t_total":97.0},{"flavor":"r-oldrel-macos-x86_64","version":"1.0.5","check_status":"NOTE","flags":"","t_install":14.0,"t_check":138.0,"t_total":152.0},{"flavor":"r-oldrel-windows-x86_64","version":"1.0.5","check_status":"NOTE","flags":"","t_install":33.0,"t_check":287.0,"t_total":320.0}]]}
