{"package":"EMbC","priority":null,"maintainer":"Joan Garriga <jgarriga@ceab.csic.es>","issues":[{}],"results":[[{"flavor":"r-devel-linux-x86_64-debian-clang","version":"2.0.4","check_status":"NOTE","flags":"","t_install":26.31,"t_check":97.62,"t_total":123.93},{"flavor":"r-devel-linux-x86_64-debian-gcc","version":"2.0.4","check_status":"NOTE","flags":"","t_install":16.48,"t_check":72.37,"t_total":88.85},{"flavor":"r-devel-linux-x86_64-fedora-clang","version":"2.0.4","check_status":"OK","flags":"","t_install":56.0,"t_check":160.18,"t_total":216.18},{"flavor":"r-devel-linux-x86_64-fedora-gcc","version":"2.0.4","check_status":"OK","flags":"","t_install":46.0,"t_check":172.52,"t_total":218.52},{"flavor":"r-devel-windows-x86_64","version":"2.0.4","check_status":"OK","flags":"","t_install":33.0,"t_check":190.0,"t_total":223.0},{"flavor":"r-patched-linux-x86_64","version":"2.0.4","check_status":"OK","flags":"","t_install":25.83,"t_check":92.38,"t_total":118.21},{"flavor":"r-release-linux-x86_64","version":"2.0.4","check_status":"OK","flags":"","t_install":27.58,"t_check":93.3,"t_total":120.88},{"flavor":"r-release-macos-arm64","version":"2.0.4","check_status":"OK","flags":"","t_install":null,"t_check":null,"t_total":null},{"flavor":"r-release-macos-x86_64","version":"2.0.4","check_status":"OK","flags":"","t_install":16.0,"t_check":110.0,"t_total":126.0},{"flavor":"r-release-windows-x86_64","version":"2.0.4","check_status":"OK","flags":"","t_install":32.0,"t_check":189.0,"t_total":221.0},{"flavor":"r-oldrel-macos-arm64","version":"2.0.4","check_status":"OK","flags":"","t_install":null,"t_check":null,"t_total":null},{"flavor":"r-oldrel-macos-x86_64","version":"2.0.4","check_status":"OK","flags":"","t_install":18.0,"t_check":77.0,"t_total":95.0},{"flavor":"r-oldrel-windows-x86_64","version":"2.0.4","check_status":"OK","flags":"","t_install":39.0,"t_check":206.0,"t_total":245.0}]]}
