{"package":"envirem","priority":null,"maintainer":"Pascal Title <pascal.title@stonybrook.edu>","issues":[{}],"results":[[{"flavor":"r-devel-linux-x86_64-debian-clang","version":"3.0","check_status":"OK","flags":"","t_install":22.27,"t_check":193.03,"t_total":215.3},{"flavor":"r-devel-linux-x86_64-debian-gcc","version":"3.0","check_status":"OK","flags":"","t_install":11.88,"t_check":114.73,"t_total":126.61},{"flavor":"r-devel-linux-x86_64-fedora-clang","version":"3.0","check_status":"OK","flags":"","t_install":null,"t_check":null,"t_total":345.96},{"flavor":"r-devel-linux-x86_64-fedora-gcc","version":"3.0","check_status":"OK","flags":"","t_install":null,"t_check":null,"t_total":330.7},{"flavor":"r-devel-windows-x86_64","version":"3.0","check_status":"OK","flags":"","t_install":21.0,"t_check":153.0,"t_total":174.0},{"flavor":"r-patched-linux-x86_64","version":"3.0","check_status":"OK","flags":"","t_install":23.56,"t_check":176.89,"t_total":200.45},{"flavor":"r-release-linux-x86_64","version":"3.0","check_status":"OK","flags":"","t_install":21.15,"t_check":180.43,"t_total":201.58},{"flavor":"r-release-macos-arm64","version":"3.0","check_status":"OK","flags":"","t_install":null,"t_check":null,"t_total":74.0},{"flavor":"r-release-macos-x86_64","version":"3.0","check_status":"OK","flags":"","t_install":null,"t_check":null,"t_total":251.0},{"flavor":"r-release-windows-x86_64","version":"3.0","check_status":"OK","flags":"","t_install":21.0,"t_check":149.0,"t_total":170.0},{"flavor":"r-oldrel-macos-arm64","version":"3.0","check_status":"OK","flags":"","t_install":null,"t_check":null,"t_total":67.0},{"flavor":"r-oldrel-macos-x86_64","version":"3.0","check_status":"OK","flags":"","t_install":null,"t_check":null,"t_total":111.0},{"flavor":"r-oldrel-windows-x86_64","version":"3.0","check_status":"OK","flags":"","t_install":29.0,"t_check":215.0,"t_total":244.0}]]}
