{"package":"funspotr","priority":null,"maintainer":"Bryan Shalloway <brshallodev@gmail.com>","issues":[{}],"results":[[{"flavor":"r-devel-linux-x86_64-debian-clang","version":"0.0.4","check_status":"OK","flags":"","t_install":4.44,"t_check":43.26,"t_total":47.7},{"flavor":"r-devel-linux-x86_64-debian-gcc","version":"0.0.4","check_status":"OK","flags":"","t_install":3.04,"t_check":33.25,"t_total":36.29},{"flavor":"r-devel-linux-x86_64-fedora-clang","version":"0.0.4","check_status":"OK","flags":"","t_install":9.0,"t_check":70.37,"t_total":79.37},{"flavor":"r-devel-linux-x86_64-fedora-gcc","version":"0.0.4","check_status":"OK","flags":"","t_install":null,"t_check":null,"t_total":74.53},{"flavor":"r-devel-windows-x86_64","version":"0.0.4","check_status":"OK","flags":"","t_install":6.0,"t_check":64.0,"t_total":70.0},{"flavor":"r-patched-linux-x86_64","version":"0.0.4","check_status":"OK","flags":"","t_install":4.87,"t_check":38.45,"t_total":43.32},{"flavor":"r-release-linux-x86_64","version":"0.0.4","check_status":"OK","flags":"","t_install":4.21,"t_check":38.49,"t_total":42.7},{"flavor":"r-release-macos-arm64","version":"0.0.4","check_status":"OK","flags":"","t_install":null,"t_check":null,"t_total":null},{"flavor":"r-release-macos-x86_64","version":"0.0.4","check_status":"OK","flags":"","t_install":3.0,"t_check":68.0,"t_total":71.0},{"flavor":"r-release-windows-x86_64","version":"0.0.4","check_status":"OK","flags":"","t_install":7.0,"t_check":61.0,"t_total":68.0},{"flavor":"r-oldrel-macos-arm64","version":"0.0.4","check_status":"OK","flags":"","t_install":null,"t_check":null,"t_total":null},{"flavor":"r-oldrel-macos-x86_64","version":"0.0.4","check_status":"OK","flags":"","t_install":3.0,"t_check":50.0,"t_total":53.0},{"flavor":"r-oldrel-windows-x86_64","version":"0.0.4","check_status":"OK","flags":"","t_install":8.0,"t_check":72.0,"t_total":80.0}]]}
