{"package":"gmvarkit","priority":null,"maintainer":"Savi Virolainen <savi.virolainen@helsinki.fi>","issues":[{}],"results":[[{"flavor":"r-devel-linux-x86_64-debian-clang","version":"2.1.4","check_status":"OK","flags":"","t_install":14.05,"t_check":344.12,"t_total":358.17},{"flavor":"r-devel-linux-x86_64-debian-gcc","version":"2.1.4","check_status":"OK","flags":"","t_install":9.35,"t_check":205.9,"t_total":215.25},{"flavor":"r-devel-linux-x86_64-fedora-gcc","version":"2.1.4","check_status":"OK","flags":"","t_install":null,"t_check":null,"t_total":581.04},{"flavor":"r-devel-macos-arm64","version":"2.1.4","check_status":"OK","flags":"","t_install":null,"t_check":null,"t_total":177.0},{"flavor":"r-devel-macos-x86_64","version":"2.1.4","check_status":"OK","flags":"","t_install":null,"t_check":null,"t_total":414.0},{"flavor":"r-devel-windows-x86_64","version":"2.1.4","check_status":"OK","flags":"","t_install":16.0,"t_check":365.0,"t_total":381.0},{"flavor":"r-patched-linux-x86_64","version":"2.1.4","check_status":"OK","flags":"","t_install":21.27,"t_check":312.88,"t_total":334.15},{"flavor":"r-release-linux-x86_64","version":"2.1.4","check_status":"OK","flags":"","t_install":null,"t_check":null,"t_total":null},{"flavor":"r-release-macos-arm64","version":"2.1.4","check_status":"OK","flags":"","t_install":null,"t_check":null,"t_total":146.0},{"flavor":"r-release-macos-x86_64","version":"2.1.4","check_status":"OK","flags":"","t_install":null,"t_check":null,"t_total":381.0},{"flavor":"r-release-windows-x86_64","version":"2.1.4","check_status":"OK","flags":"","t_install":21.0,"t_check":505.0,"t_total":526.0},{"flavor":"r-oldrel-macos-arm64","version":"2.1.4","check_status":"OK","flags":"","t_install":null,"t_check":null,"t_total":null},{"flavor":"r-oldrel-macos-x86_64","version":"2.1.4","check_status":"OK","flags":"","t_install":null,"t_check":null,"t_total":376.0},{"flavor":"r-oldrel-windows-x86_64","version":"2.1.4","check_status":"OK","flags":"","t_install":19.0,"t_check":494.0,"t_total":513.0}]]}
