{"package":"loon.shiny","priority":null,"maintainer":"Zehao Xu <z267xu@gmail.com>","issues":[{}],"results":[[{"flavor":"r-devel-linux-x86_64-debian-clang","version":"1.0.4","check_status":"OK","flags":"","t_install":22.33,"t_check":182.64,"t_total":204.97},{"flavor":"r-devel-linux-x86_64-debian-gcc","version":"1.0.4","check_status":"OK","flags":"","t_install":15.87,"t_check":136.9,"t_total":152.77},{"flavor":"r-devel-linux-x86_64-fedora-clang","version":"1.0.4","check_status":"OK","flags":"","t_install":44.0,"t_check":312.43,"t_total":356.43},{"flavor":"r-devel-linux-x86_64-fedora-gcc","version":"1.0.4","check_status":"OK","flags":"","t_install":43.0,"t_check":309.82,"t_total":352.82},{"flavor":"r-devel-windows-x86_64","version":"1.0.4","check_status":"OK","flags":"","t_install":23.0,"t_check":209.0,"t_total":232.0},{"flavor":"r-patched-linux-x86_64","version":"1.0.4","check_status":"OK","flags":"","t_install":25.84,"t_check":183.53,"t_total":209.37},{"flavor":"r-release-linux-x86_64","version":"1.0.4","check_status":"OK","flags":"","t_install":25.94,"t_check":181.04,"t_total":206.98},{"flavor":"r-release-macos-arm64","version":"1.0.4","check_status":"OK","flags":"","t_install":null,"t_check":null,"t_total":null},{"flavor":"r-release-macos-x86_64","version":"1.0.4","check_status":"OK","flags":"","t_install":21.0,"t_check":234.0,"t_total":255.0},{"flavor":"r-release-windows-x86_64","version":"1.0.4","check_status":"OK","flags":"","t_install":21.0,"t_check":184.0,"t_total":205.0},{"flavor":"r-oldrel-macos-arm64","version":"1.0.4","check_status":"OK","flags":"","t_install":null,"t_check":null,"t_total":null},{"flavor":"r-oldrel-macos-x86_64","version":"1.0.4","check_status":"OK","flags":"","t_install":21.0,"t_check":256.0,"t_total":277.0},{"flavor":"r-oldrel-windows-x86_64","version":"1.0.4","check_status":"OK","flags":"","t_install":29.0,"t_check":215.0,"t_total":244.0}]]}
