{"package":"MedianaDesigner","priority":null,"maintainer":"Alex Dmitrienko <admitrienko@mediana.us>","issues":[{}],"results":[[{"flavor":"r-devel-linux-x86_64-debian-clang","version":"0.13","check_status":"NOTE","flags":"","t_install":84.93,"t_check":384.68,"t_total":469.61},{"flavor":"r-devel-linux-x86_64-debian-gcc","version":"0.13","check_status":"NOTE","flags":"","t_install":60.59,"t_check":242.54,"t_total":303.13},{"flavor":"r-devel-linux-x86_64-fedora-clang","version":"0.13","check_status":"NOTE","flags":"","t_install":null,"t_check":null,"t_total":783.75},{"flavor":"r-devel-linux-x86_64-fedora-gcc","version":"0.13","check_status":"NOTE","flags":"","t_install":null,"t_check":null,"t_total":768.29},{"flavor":"r-devel-windows-x86_64","version":"0.13","check_status":"NOTE","flags":"","t_install":81.0,"t_check":381.0,"t_total":462.0},{"flavor":"r-patched-linux-x86_64","version":"0.13","check_status":"NOTE","flags":"","t_install":84.6,"t_check":365.18,"t_total":449.78},{"flavor":"r-release-linux-x86_64","version":"0.13","check_status":"NOTE","flags":"","t_install":78.01,"t_check":363.43,"t_total":441.44},{"flavor":"r-release-macos-arm64","version":"0.13","check_status":"NOTE","flags":"","t_install":null,"t_check":null,"t_total":207.0},{"flavor":"r-release-macos-x86_64","version":"0.13","check_status":"NOTE","flags":"","t_install":null,"t_check":null,"t_total":438.0},{"flavor":"r-release-windows-x86_64","version":"0.13","check_status":"NOTE","flags":"","t_install":76.0,"t_check":376.0,"t_total":452.0},{"flavor":"r-oldrel-macos-arm64","version":"0.13","check_status":"NOTE","flags":"","t_install":null,"t_check":null,"t_total":189.0},{"flavor":"r-oldrel-macos-x86_64","version":"0.13","check_status":"NOTE","flags":"","t_install":null,"t_check":null,"t_total":312.0},{"flavor":"r-oldrel-windows-x86_64","version":"0.13","check_status":"NOTE","flags":"","t_install":91.0,"t_check":503.0,"t_total":594.0}]]}
