{"package":"MPTinR","priority":null,"maintainer":"Henrik Singmann <singmann@gmail.com>","issues":[{}],"results":[[{"flavor":"r-devel-linux-x86_64-debian-clang","version":"1.14.1","check_status":"NOTE","flags":"","t_install":51.89,"t_check":192.73,"t_total":244.62},{"flavor":"r-devel-linux-x86_64-debian-gcc","version":"1.14.1","check_status":"NOTE","flags":"","t_install":38.41,"t_check":130.82,"t_total":169.23},{"flavor":"r-devel-linux-x86_64-fedora-clang","version":"1.14.1","check_status":"NOTE","flags":"","t_install":null,"t_check":null,"t_total":383.66},{"flavor":"r-devel-linux-x86_64-fedora-gcc","version":"1.14.1","check_status":"NOTE","flags":"","t_install":null,"t_check":null,"t_total":413.06},{"flavor":"r-devel-windows-x86_64","version":"1.14.1","check_status":"NOTE","flags":"","t_install":54.0,"t_check":239.0,"t_total":293.0},{"flavor":"r-patched-linux-x86_64","version":"1.14.1","check_status":"NOTE","flags":"","t_install":53.33,"t_check":189.83,"t_total":243.16},{"flavor":"r-release-linux-x86_64","version":"1.14.1","check_status":"NOTE","flags":"","t_install":54.15,"t_check":191.3,"t_total":245.45},{"flavor":"r-release-macos-arm64","version":"1.14.1","check_status":"NOTE","flags":"","t_install":null,"t_check":null,"t_total":120.0},{"flavor":"r-release-macos-x86_64","version":"1.14.1","check_status":"NOTE","flags":"","t_install":null,"t_check":null,"t_total":235.0},{"flavor":"r-release-windows-x86_64","version":"1.14.1","check_status":"NOTE","flags":"","t_install":53.0,"t_check":239.0,"t_total":292.0},{"flavor":"r-oldrel-macos-arm64","version":"1.14.1","check_status":"NOTE","flags":"","t_install":null,"t_check":null,"t_total":107.0},{"flavor":"r-oldrel-macos-x86_64","version":"1.14.1","check_status":"NOTE","flags":"","t_install":null,"t_check":null,"t_total":295.0},{"flavor":"r-oldrel-windows-x86_64","version":"1.14.1","check_status":"NOTE","flags":"","t_install":63.0,"t_check":291.0,"t_total":354.0}]]}
