{"package":"oncoPredict","priority":null,"maintainer":"Robert Gruener <rgruener@umn.edu>","issues":[{}],"results":[[{"flavor":"r-devel-linux-x86_64-debian-clang","version":"1.2","check_status":"OK","flags":"","t_install":54.51,"t_check":584.15,"t_total":638.66},{"flavor":"r-devel-linux-x86_64-debian-gcc","version":"1.2","check_status":"OK","flags":"","t_install":41.63,"t_check":425.45,"t_total":467.08},{"flavor":"r-devel-linux-x86_64-fedora-clang","version":"1.2","check_status":"OK","flags":"","t_install":null,"t_check":null,"t_total":1020.69},{"flavor":"r-devel-linux-x86_64-fedora-gcc","version":"1.2","check_status":"OK","flags":"","t_install":null,"t_check":null,"t_total":1007.4},{"flavor":"r-devel-windows-x86_64","version":"1.2","check_status":"OK","flags":"","t_install":58.0,"t_check":460.0,"t_total":518.0},{"flavor":"r-patched-linux-x86_64","version":"1.2","check_status":"OK","flags":"","t_install":54.34,"t_check":552.01,"t_total":606.35},{"flavor":"r-release-linux-x86_64","version":"1.2","check_status":"OK","flags":"","t_install":51.95,"t_check":548.99,"t_total":600.94},{"flavor":"r-release-macos-arm64","version":"1.2","check_status":"ERROR","flags":"","t_install":null,"t_check":null,"t_total":5.0},{"flavor":"r-release-macos-x86_64","version":"1.2","check_status":"ERROR","flags":"","t_install":null,"t_check":null,"t_total":7.0},{"flavor":"r-release-windows-x86_64","version":"1.2","check_status":"OK","flags":"","t_install":56.0,"t_check":464.0,"t_total":520.0},{"flavor":"r-oldrel-macos-arm64","version":"1.2","check_status":"ERROR","flags":"","t_install":null,"t_check":null,"t_total":10.0},{"flavor":"r-oldrel-macos-x86_64","version":"1.2","check_status":"ERROR","flags":"","t_install":null,"t_check":null,"t_total":11.0},{"flavor":"r-oldrel-windows-x86_64","version":"1.2","check_status":"OK","flags":"","t_install":78.0,"t_check":619.0,"t_total":697.0}]]}
