{"package":"paws.machine.learning","priority":null,"maintainer":"Dyfan Jones <dyfan.r.jones@gmail.com>","issues":[{}],"results":[[{"flavor":"r-devel-linux-x86_64-debian-clang","version":"0.9.0","check_status":"OK","flags":"","t_install":144.3,"t_check":353.68,"t_total":497.98},{"flavor":"r-devel-linux-x86_64-debian-gcc","version":"0.9.0","check_status":"OK","flags":"","t_install":91.34,"t_check":234.64,"t_total":325.98},{"flavor":"r-devel-linux-x86_64-fedora-clang","version":"0.9.0","check_status":"OK","flags":"","t_install":240.0,"t_check":550.27,"t_total":790.27},{"flavor":"r-devel-linux-x86_64-fedora-gcc","version":"0.9.0","check_status":"OK","flags":"","t_install":239.0,"t_check":500.03,"t_total":739.03},{"flavor":"r-devel-windows-x86_64","version":"0.9.0","check_status":"OK","flags":"","t_install":152.0,"t_check":702.0,"t_total":854.0},{"flavor":"r-patched-linux-x86_64","version":"0.9.0","check_status":"OK","flags":"","t_install":166.17,"t_check":285.99,"t_total":452.16},{"flavor":"r-release-linux-x86_64","version":"0.9.0","check_status":"OK","flags":"","t_install":150.43,"t_check":285.92,"t_total":436.35},{"flavor":"r-release-macos-arm64","version":"0.9.0","check_status":"OK","flags":"","t_install":null,"t_check":null,"t_total":null},{"flavor":"r-release-macos-x86_64","version":"0.9.0","check_status":"OK","flags":"","t_install":93.0,"t_check":281.0,"t_total":374.0},{"flavor":"r-release-windows-x86_64","version":"0.9.0","check_status":"OK","flags":"","t_install":147.0,"t_check":606.0,"t_total":753.0},{"flavor":"r-oldrel-macos-arm64","version":"0.9.0","check_status":"NOTE","flags":"","t_install":null,"t_check":null,"t_total":null},{"flavor":"r-oldrel-macos-x86_64","version":"0.9.0","check_status":"NOTE","flags":"","t_install":98.0,"t_check":224.0,"t_total":322.0},{"flavor":"r-oldrel-windows-x86_64","version":"0.9.0","check_status":"NOTE","flags":"","t_install":213.0,"t_check":651.0,"t_total":864.0}]]}
