{"package":"pivmet","priority":null,"maintainer":"Leonardo Egidi <legidi@units.it>","issues":[{}],"results":[[{"flavor":"r-devel-linux-x86_64-debian-clang","version":"0.6.0","check_status":"NOTE","flags":"","t_install":23.41,"t_check":334.09,"t_total":357.5},{"flavor":"r-devel-linux-x86_64-debian-gcc","version":"0.6.0","check_status":"NOTE","flags":"","t_install":18.38,"t_check":209.01,"t_total":227.39},{"flavor":"r-devel-linux-x86_64-fedora-clang","version":"0.6.0","check_status":"OK","flags":"","t_install":68.0,"t_check":525.45,"t_total":593.45},{"flavor":"r-devel-linux-x86_64-fedora-gcc","version":"0.6.0","check_status":"OK","flags":"","t_install":55.0,"t_check":486.42999999999997,"t_total":541.43},{"flavor":"r-devel-windows-x86_64","version":"0.6.0","check_status":"OK","flags":"","t_install":18.0,"t_check":344.0,"t_total":362.0},{"flavor":"r-patched-linux-x86_64","version":"0.6.0","check_status":"OK","flags":"","t_install":24.56,"t_check":325.98,"t_total":350.54},{"flavor":"r-release-linux-x86_64","version":"0.6.0","check_status":"OK","flags":"","t_install":23.25,"t_check":320.25,"t_total":343.5},{"flavor":"r-release-macos-arm64","version":"0.6.0","check_status":"OK","flags":"","t_install":6.0,"t_check":140.0,"t_total":146.0},{"flavor":"r-release-macos-x86_64","version":"0.6.0","check_status":"OK","flags":"","t_install":16.0,"t_check":329.0,"t_total":345.0},{"flavor":"r-release-windows-x86_64","version":"0.6.0","check_status":"OK","flags":"","t_install":17.0,"t_check":340.0,"t_total":357.0},{"flavor":"r-oldrel-macos-arm64","version":"0.6.0","check_status":"OK","flags":"","t_install":6.0,"t_check":133.0,"t_total":139.0},{"flavor":"r-oldrel-macos-x86_64","version":"0.6.0","check_status":"OK","flags":"","t_install":14.0,"t_check":323.0,"t_total":337.0},{"flavor":"r-oldrel-windows-x86_64","version":"0.6.0","check_status":"OK","flags":"","t_install":25.0,"t_check":472.0,"t_total":497.0}]]}
