{"package":"PortfolioTesteR","priority":null,"maintainer":"Alberto Pallotta <pallottaalberto@gmail.com>","issues":[{}],"results":[[{"flavor":"r-devel-linux-x86_64-debian-clang","version":"0.1.4","check_status":"OK","flags":"","t_install":12.74,"t_check":327.52,"t_total":340.26},{"flavor":"r-devel-linux-x86_64-debian-gcc","version":"0.1.4","check_status":"OK","flags":"","t_install":8.23,"t_check":250.75,"t_total":258.98},{"flavor":"r-devel-linux-x86_64-fedora-clang","version":"0.1.4","check_status":"OK","flags":"","t_install":25.0,"t_check":null,"t_total":null},{"flavor":"r-devel-linux-x86_64-fedora-gcc","version":"0.1.4","check_status":"OK","flags":"","t_install":57.0,"t_check":438.87,"t_total":495.87},{"flavor":"r-devel-windows-x86_64","version":"0.1.4","check_status":"OK","flags":"","t_install":18.0,"t_check":219.0,"t_total":237.0},{"flavor":"r-patched-linux-x86_64","version":"0.1.4","check_status":"OK","flags":"","t_install":14.83,"t_check":290.53,"t_total":305.36},{"flavor":"r-release-linux-x86_64","version":"0.1.4","check_status":"OK","flags":"","t_install":12.15,"t_check":296.91,"t_total":309.06},{"flavor":"r-release-macos-arm64","version":"0.1.4","check_status":"OK","flags":"","t_install":null,"t_check":null,"t_total":null},{"flavor":"r-release-macos-x86_64","version":"0.1.4","check_status":"OK","flags":"","t_install":13.0,"t_check":197.0,"t_total":210.0},{"flavor":"r-release-windows-x86_64","version":"0.1.4","check_status":"OK","flags":"","t_install":15.0,"t_check":216.0,"t_total":231.0},{"flavor":"r-oldrel-macos-arm64","version":"0.1.4","check_status":"ERROR","flags":"","t_install":3.0,"t_check":43.0,"t_total":46.0},{"flavor":"r-oldrel-macos-x86_64","version":"0.1.4","check_status":"ERROR","flags":"","t_install":20.0,"t_check":172.0,"t_total":192.0},{"flavor":"r-oldrel-windows-x86_64","version":"0.1.4","check_status":"ERROR","flags":"","t_install":20.0,"t_check":194.0,"t_total":214.0}]]}
