{"package":"rcbayes","priority":null,"maintainer":"Jessie Yeung <jessieyeung1@gmail.com>","issues":[{}],"results":[[{"flavor":"r-devel-linux-x86_64-debian-clang","version":"0.3.0","check_status":"OK","flags":"","t_install":468.88,"t_check":199.36,"t_total":668.24},{"flavor":"r-devel-linux-x86_64-debian-gcc","version":"0.3.0","check_status":"OK","flags":"","t_install":406.92,"t_check":173.37,"t_total":580.29},{"flavor":"r-devel-linux-x86_64-fedora-clang","version":"0.3.0","check_status":"NOTE","flags":"","t_install":null,"t_check":null,"t_total":986.62},{"flavor":"r-devel-linux-x86_64-fedora-gcc","version":"0.3.0","check_status":"NOTE","flags":"","t_install":null,"t_check":null,"t_total":1337.33},{"flavor":"r-devel-windows-x86_64","version":"0.3.0","check_status":"OK","flags":"","t_install":520.0,"t_check":228.0,"t_total":748.0},{"flavor":"r-patched-linux-x86_64","version":"0.3.0","check_status":"OK","flags":"","t_install":532.74,"t_check":233.26,"t_total":766.0},{"flavor":"r-release-linux-x86_64","version":"0.3.0","check_status":"OK","flags":"","t_install":533.41,"t_check":230.85,"t_total":764.26},{"flavor":"r-release-macos-arm64","version":"0.3.0","check_status":"OK","flags":"","t_install":null,"t_check":null,"t_total":282.0},{"flavor":"r-release-macos-x86_64","version":"0.3.0","check_status":"OK","flags":"","t_install":null,"t_check":null,"t_total":300.0},{"flavor":"r-release-windows-x86_64","version":"0.3.0","check_status":"OK","flags":"","t_install":498.0,"t_check":232.0,"t_total":730.0},{"flavor":"r-oldrel-macos-arm64","version":"0.3.0","check_status":"NOTE","flags":"","t_install":null,"t_check":null,"t_total":287.0},{"flavor":"r-oldrel-macos-x86_64","version":"0.3.0","check_status":"NOTE","flags":"","t_install":null,"t_check":null,"t_total":289.0},{"flavor":"r-oldrel-windows-x86_64","version":"0.3.0","check_status":"NOTE","flags":"","t_install":572.0,"t_check":279.0,"t_total":851.0}]]}
