{"package":"samc","priority":null,"maintainer":"Andrew Marx <ajm.rpackages@gmail.com>","issues":[{}],"results":[[{"flavor":"r-devel-linux-x86_64-debian-clang","version":"4.0.0","check_status":"OK","flags":"","t_install":153.93,"t_check":382.7,"t_total":536.63},{"flavor":"r-devel-linux-x86_64-debian-gcc","version":"4.0.0","check_status":"OK","flags":"","t_install":116.52,"t_check":270.47,"t_total":386.99},{"flavor":"r-devel-linux-x86_64-fedora-clang","version":"4.0.0","check_status":"OK","flags":"","t_install":null,"t_check":null,"t_total":871.58},{"flavor":"r-devel-linux-x86_64-fedora-gcc","version":"4.0.0","check_status":"OK","flags":"","t_install":null,"t_check":null,"t_total":913.19},{"flavor":"r-devel-windows-x86_64","version":"4.0.0","check_status":"OK","flags":"","t_install":154.0,"t_check":327.0,"t_total":481.0},{"flavor":"r-patched-linux-x86_64","version":"4.0.0","check_status":"OK","flags":"","t_install":164.98,"t_check":378.72,"t_total":543.7},{"flavor":"r-release-linux-x86_64","version":"4.0.0","check_status":"OK","flags":"","t_install":167.58,"t_check":377.25,"t_total":544.83},{"flavor":"r-release-macos-arm64","version":"4.0.0","check_status":"OK","flags":"","t_install":null,"t_check":null,"t_total":219.0},{"flavor":"r-release-macos-x86_64","version":"4.0.0","check_status":"OK","flags":"","t_install":null,"t_check":null,"t_total":412.0},{"flavor":"r-release-windows-x86_64","version":"4.0.0","check_status":"OK","flags":"","t_install":154.0,"t_check":324.0,"t_total":478.0},{"flavor":"r-oldrel-macos-arm64","version":"4.0.0","check_status":"NOTE","flags":"","t_install":null,"t_check":null,"t_total":213.0},{"flavor":"r-oldrel-macos-x86_64","version":"4.0.0","check_status":"NOTE","flags":"","t_install":null,"t_check":null,"t_total":335.0},{"flavor":"r-oldrel-windows-x86_64","version":"4.0.0","check_status":"OK","flags":"","t_install":191.0,"t_check":466.0,"t_total":657.0}]]}
