{"package":"sequential.pops","priority":null,"maintainer":"Diego F Rincon <diego.rincon@wsu.edu>","issues":[{}],"results":[[{"flavor":"r-devel-linux-x86_64-debian-clang","version":"0.1.1","check_status":"OK","flags":"","t_install":12.91,"t_check":243.68,"t_total":256.59},{"flavor":"r-devel-linux-x86_64-debian-gcc","version":"0.1.1","check_status":"OK","flags":"","t_install":8.35,"t_check":163.15,"t_total":171.5},{"flavor":"r-devel-linux-x86_64-fedora-clang","version":"0.1.1","check_status":"OK","flags":"","t_install":null,"t_check":null,"t_total":401.8},{"flavor":"r-devel-linux-x86_64-fedora-gcc","version":"0.1.1","check_status":"OK","flags":"","t_install":null,"t_check":null,"t_total":415.07},{"flavor":"r-devel-windows-x86_64","version":"0.1.1","check_status":"OK","flags":"","t_install":12.0,"t_check":257.0,"t_total":269.0},{"flavor":"r-patched-linux-x86_64","version":"0.1.1","check_status":"OK","flags":"","t_install":11.78,"t_check":229.46,"t_total":241.24},{"flavor":"r-release-linux-x86_64","version":"0.1.1","check_status":"OK","flags":"","t_install":11.42,"t_check":229.53,"t_total":240.95},{"flavor":"r-release-macos-arm64","version":"0.1.1","check_status":"OK","flags":"","t_install":null,"t_check":null,"t_total":130.0},{"flavor":"r-release-macos-x86_64","version":"0.1.1","check_status":"OK","flags":"","t_install":null,"t_check":null,"t_total":256.0},{"flavor":"r-release-windows-x86_64","version":"0.1.1","check_status":"OK","flags":"","t_install":12.0,"t_check":268.0,"t_total":280.0},{"flavor":"r-oldrel-macos-arm64","version":"0.1.1","check_status":"OK","flags":"","t_install":null,"t_check":null,"t_total":128.0},{"flavor":"r-oldrel-macos-x86_64","version":"0.1.1","check_status":"OK","flags":"","t_install":null,"t_check":null,"t_total":290.0},{"flavor":"r-oldrel-windows-x86_64","version":"0.1.1","check_status":"OK","flags":"","t_install":17.0,"t_check":344.0,"t_total":361.0}]]}
