{"package":"spup","priority":null,"maintainer":"Kasia Sawicka <katwic55@ceh.ac.uk>","issues":[{}],"results":[[{"flavor":"r-devel-linux-x86_64-debian-clang","version":"1.4-0","check_status":"OK","flags":"","t_install":31.64,"t_check":383.22,"t_total":414.86},{"flavor":"r-devel-linux-x86_64-debian-gcc","version":"1.4-0","check_status":"OK","flags":"","t_install":20.49,"t_check":244.29,"t_total":264.78},{"flavor":"r-devel-linux-x86_64-fedora-clang","version":"1.4-0","check_status":"OK","flags":"","t_install":null,"t_check":null,"t_total":669.5},{"flavor":"r-devel-linux-x86_64-fedora-gcc","version":"1.4-0","check_status":"OK","flags":"","t_install":null,"t_check":null,"t_total":671.03},{"flavor":"r-devel-windows-x86_64","version":"1.4-0","check_status":"OK","flags":"","t_install":29.0,"t_check":293.0,"t_total":322.0},{"flavor":"r-patched-linux-x86_64","version":"1.4-0","check_status":"OK","flags":"","t_install":30.49,"t_check":356.85,"t_total":387.34},{"flavor":"r-release-linux-x86_64","version":"1.4-0","check_status":"OK","flags":"","t_install":29.86,"t_check":365.14,"t_total":395.0},{"flavor":"r-release-macos-arm64","version":"1.4-0","check_status":"OK","flags":"","t_install":null,"t_check":null,"t_total":149.0},{"flavor":"r-release-macos-x86_64","version":"1.4-0","check_status":"OK","flags":"","t_install":null,"t_check":null,"t_total":323.0},{"flavor":"r-release-windows-x86_64","version":"1.4-0","check_status":"OK","flags":"","t_install":30.0,"t_check":288.0,"t_total":318.0},{"flavor":"r-oldrel-macos-arm64","version":"1.4-0","check_status":"OK","flags":"","t_install":null,"t_check":null,"t_total":149.0},{"flavor":"r-oldrel-macos-x86_64","version":"1.4-0","check_status":"OK","flags":"","t_install":null,"t_check":null,"t_total":261.0},{"flavor":"r-oldrel-windows-x86_64","version":"1.4-0","check_status":"OK","flags":"","t_install":40.0,"t_check":421.0,"t_total":461.0}]]}
