{"package":"survivalMPLdc","priority":null,"maintainer":"Jing Xu <kenny.xu@duke-nus.edu.sg>","issues":[{}],"results":[[{"flavor":"r-devel-linux-x86_64-debian-clang","version":"0.1.1","check_status":"NOTE","flags":"","t_install":13.67,"t_check":853.15,"t_total":866.82},{"flavor":"r-devel-linux-x86_64-debian-gcc","version":"0.1.1","check_status":"NOTE","flags":"","t_install":8.67,"t_check":610.03,"t_total":618.7},{"flavor":"r-devel-linux-x86_64-fedora-clang","version":"0.1.1","check_status":"NOTE","flags":"","t_install":null,"t_check":null,"t_total":1401.89},{"flavor":"r-devel-linux-x86_64-fedora-gcc","version":"0.1.1","check_status":"NOTE","flags":"","t_install":null,"t_check":null,"t_total":1454.83},{"flavor":"r-devel-windows-x86_64","version":"0.1.1","check_status":"NOTE","flags":"","t_install":13.0,"t_check":1271.0,"t_total":1284.0},{"flavor":"r-patched-linux-x86_64","version":"0.1.1","check_status":"NOTE","flags":"","t_install":14.08,"t_check":828.45,"t_total":842.53},{"flavor":"r-release-linux-x86_64","version":"0.1.1","check_status":"NOTE","flags":"","t_install":12.87,"t_check":843.14,"t_total":856.01},{"flavor":"r-release-macos-arm64","version":"0.1.1","check_status":"NOTE","flags":"","t_install":null,"t_check":null,"t_total":545.0},{"flavor":"r-release-macos-x86_64","version":"0.1.1","check_status":"NOTE","flags":"","t_install":null,"t_check":null,"t_total":1030.0},{"flavor":"r-release-windows-x86_64","version":"0.1.1","check_status":"NOTE","flags":"","t_install":14.0,"t_check":1295.0,"t_total":1309.0},{"flavor":"r-oldrel-macos-arm64","version":"0.1.1","check_status":"NOTE","flags":"","t_install":null,"t_check":null,"t_total":487.0},{"flavor":"r-oldrel-macos-x86_64","version":"0.1.1","check_status":"NOTE","flags":"","t_install":null,"t_check":null,"t_total":760.0},{"flavor":"r-oldrel-windows-x86_64","version":"0.1.1","check_status":"NOTE","flags":"","t_install":19.0,"t_check":1595.0,"t_total":1614.0}]]}
