{"package":"trouBBlme4SolveR","priority":null,"maintainer":"Iago Giné-Vázquez <iago.gin-vaz@protonmail.com>","issues":[{}],"results":[[{"flavor":"r-devel-linux-x86_64-debian-clang","version":"0.1.4","check_status":"OK","flags":"","t_install":8.83,"t_check":173.36,"t_total":182.19},{"flavor":"r-devel-linux-x86_64-debian-gcc","version":"0.1.4","check_status":"OK","flags":"","t_install":5.86,"t_check":128.55,"t_total":134.41},{"flavor":"r-devel-linux-x86_64-fedora-clang","version":"0.1.4","check_status":"OK","flags":"","t_install":13.0,"t_check":289.1,"t_total":302.1},{"flavor":"r-devel-linux-x86_64-fedora-gcc","version":"0.1.4","check_status":"OK","flags":"","t_install":13.0,"t_check":305.26,"t_total":318.26},{"flavor":"r-devel-windows-x86_64","version":"0.1.4","check_status":"OK","flags":"","t_install":10.0,"t_check":218.0,"t_total":228.0},{"flavor":"r-patched-linux-x86_64","version":"0.1.4","check_status":"OK","flags":"","t_install":7.75,"t_check":176.53,"t_total":184.28},{"flavor":"r-release-linux-x86_64","version":"0.1.4","check_status":"OK","flags":"","t_install":7.83,"t_check":175.47,"t_total":183.3},{"flavor":"r-release-macos-arm64","version":"0.1.4","check_status":"OK","flags":"","t_install":2.0,"t_check":53.0,"t_total":55.0},{"flavor":"r-release-macos-x86_64","version":"0.1.4","check_status":"OK","flags":"","t_install":7.0,"t_check":202.0,"t_total":209.0},{"flavor":"r-release-windows-x86_64","version":"0.1.4","check_status":"OK","flags":"","t_install":10.0,"t_check":220.0,"t_total":230.0},{"flavor":"r-oldrel-macos-arm64","version":"0.1.4","check_status":"OK","flags":"","t_install":2.0,"t_check":56.0,"t_total":58.0},{"flavor":"r-oldrel-macos-x86_64","version":"0.1.4","check_status":"OK","flags":"","t_install":6.0,"t_check":209.0,"t_total":215.0},{"flavor":"r-oldrel-windows-x86_64","version":"0.1.4","check_status":"OK","flags":"","t_install":12.0,"t_check":282.0,"t_total":294.0}]]}
