{"package":"tsmarch","priority":null,"maintainer":"Alexios Galanos <alexios@4dscape.com>","issues":[{}],"results":[[{"flavor":"r-devel-linux-x86_64-debian-clang","version":"1.0.0","check_status":"OK","flags":"","t_install":135.02,"t_check":776.72,"t_total":911.74},{"flavor":"r-devel-linux-x86_64-debian-gcc","version":"1.0.0","check_status":"OK","flags":"","t_install":98.46,"t_check":518.0,"t_total":616.46},{"flavor":"r-devel-linux-x86_64-fedora-clang","version":"1.0.0","check_status":"OK","flags":"","t_install":259.0,"t_check":1296.14,"t_total":1555.14},{"flavor":"r-devel-linux-x86_64-fedora-gcc","version":"1.0.0","check_status":"OK","flags":"","t_install":422.0,"t_check":1137.73,"t_total":1559.73},{"flavor":"r-devel-windows-x86_64","version":"1.0.0","check_status":"OK","flags":"","t_install":190.0,"t_check":715.0,"t_total":905.0},{"flavor":"r-patched-linux-x86_64","version":"1.0.0","check_status":"OK","flags":"","t_install":145.91,"t_check":721.88,"t_total":867.79},{"flavor":"r-release-linux-x86_64","version":"1.0.0","check_status":"OK","flags":"","t_install":140.36,"t_check":735.27,"t_total":875.63},{"flavor":"r-release-macos-arm64","version":"1.0.0","check_status":"OK","flags":"","t_install":null,"t_check":null,"t_total":null},{"flavor":"r-release-macos-x86_64","version":"1.0.0","check_status":"OK","flags":"","t_install":56.0,"t_check":627.0,"t_total":683.0},{"flavor":"r-release-windows-x86_64","version":"1.0.0","check_status":"OK","flags":"","t_install":156.0,"t_check":706.0,"t_total":862.0},{"flavor":"r-oldrel-macos-arm64","version":"1.0.0","check_status":"NOTE","flags":"","t_install":null,"t_check":null,"t_total":null},{"flavor":"r-oldrel-macos-x86_64","version":"1.0.0","check_status":"NOTE","flags":"","t_install":28.0,"t_check":310.0,"t_total":338.0},{"flavor":"r-oldrel-windows-x86_64","version":"1.0.0","check_status":"NOTE","flags":"","t_install":197.0,"t_check":963.0,"t_total":1160.0}]]}
